pornLib/__init__.py
pornlib-1.0.2.dist-info/METADATA
pornlib-1.0.2.dist-info/WHEEL
pornlib-1.0.2.dist-info/RECORD
